compact_rienet/__init__.py
compact_rienet/custom_layers.py
compact_rienet/dtype_utils.py
compact_rienet/layers.py
compact_rienet/losses.py
compact_rienet/version.py
compact_rienet-1.2.0.dist-info/licenses/LICENSE
compact_rienet-1.2.0.dist-info/METADATA
compact_rienet-1.2.0.dist-info/WHEEL
compact_rienet-1.2.0.dist-info/top_level.txt
compact_rienet-1.2.0.dist-info/RECORD
