Metadata-Version: 2.4
Name: compact-rienet
Version: 1.2.0
Summary: A Compact Recurrent-Invariant Eigenvalue Network for Portfolio Optimization
Home-page: https://github.com/bongiornoc/Compact-RIEnet
Author: Christian Bongiorno
Author-email: Christian Bongiorno <christian.bongiorno@centralesupelec.fr>
Maintainer-email: Christian Bongiorno <christian.bongiorno@centralesupelec.fr>
License: MIT
Project-URL: Homepage, https://github.com/bongiornoc/Compact-RIEnet
Project-URL: Bug Tracker, https://github.com/bongiornoc/Compact-RIEnet/issues
Project-URL: Documentation, https://github.com/bongiornoc/Compact-RIEnet
Project-URL: Source Code, https://github.com/bongiornoc/Compact-RIEnet
Keywords: portfolio optimization,neural networks,finance,machine learning,tensorflow,eigenvalue decomposition,recurrent neural networks,covariance estimation
Classifier: Development Status :: 5 - Production/Stable
Classifier: Intended Audience :: Science/Research
Classifier: Intended Audience :: Financial and Insurance Industry
Classifier: License :: OSI Approved :: MIT License
Classifier: Operating System :: OS Independent
Classifier: Programming Language :: Python :: 3
Classifier: Programming Language :: Python :: 3.8
Classifier: Programming Language :: Python :: 3.9
Classifier: Programming Language :: Python :: 3.10
Classifier: Programming Language :: Python :: 3.11
Classifier: Topic :: Scientific/Engineering :: Artificial Intelligence
Classifier: Topic :: Office/Business :: Financial :: Investment
Classifier: Topic :: Scientific/Engineering :: Mathematics
Requires-Python: >=3.8
License-File: LICENSE
Requires-Dist: tensorflow>=2.10.0
Requires-Dist: keras>=2.10.0
Requires-Dist: numpy>=1.21.0
Provides-Extra: dev
Requires-Dist: pytest>=6.0; extra == "dev"
Requires-Dist: pytest-cov>=2.0; extra == "dev"
Requires-Dist: black>=22.0; extra == "dev"
Requires-Dist: flake8>=4.0; extra == "dev"
Requires-Dist: mypy>=0.900; extra == "dev"
Provides-Extra: examples
Requires-Dist: matplotlib>=3.5.0; extra == "examples"
Requires-Dist: pandas>=1.3.0; extra == "examples"
Requires-Dist: jupyter>=1.0.0; extra == "examples"
Dynamic: author
Dynamic: home-page
Dynamic: license-file
Dynamic: requires-python
